lolapi/APIs.py
lolapi/__init__.py
lolapi/dbtest.py
lolapi/funtions.py
LOLapikr-1.1.5.dist-info/LICENSE
LOLapikr-1.1.5.dist-info/METADATA
LOLapikr-1.1.5.dist-info/WHEEL
LOLapikr-1.1.5.dist-info/top_level.txt
LOLapikr-1.1.5.dist-info/RECORD
