Metadata-Version: 2.1
Name: LOLapikr
Version: 1.1.5
Summary: functions using Riot's League of Legend API.
Home-page: https://github.com/dhk1349/League_of_Legend_4U
Author: dhk1349
Author-email: dhk1349@gmail.com
License: MIT
Platform: UNKNOWN
Classifier: Programming Language :: Python :: 3
Classifier: License :: OSI Approved :: MIT License
Classifier: Operating System :: OS Independent
